sklearn_json/__init__.py
sklearn_json/classification.py
sklearn_json/csr.py
sklearn_json/regression.py
test/__init__.py
test/test_classification.py
test/test_regression.py
sklearn_json-0.1.0.dist-info/LICENSE
sklearn_json-0.1.0.dist-info/METADATA
sklearn_json-0.1.0.dist-info/WHEEL
sklearn_json-0.1.0.dist-info/top_level.txt
sklearn_json-0.1.0.dist-info/RECORD
