Metadata-Version: 2.1
Name: sklearn-json
Version: 0.1.0
Summary: A safe, transparent way to share and deploy scikit-learn models.
Home-page: https://github.com/mlrequest/sklearn-json
Author: Mathieu Rodrigue
Author-email: support@mlrequest.com
License: UNKNOWN
Platform: UNKNOWN
Classifier: Programming Language :: Python :: 3
Classifier: License :: OSI Approved :: MIT License
Classifier: Operating System :: OS Independent
Requires-Python: >=3.5
